manim_algorithm/__init__.py
manim_algorithm/array.py
manim_algorithm/code.py
manim_algorithm/node.py
manim_algorithm/examples/__init__.py
manim_algorithm/examples/array.py
manim_algorithm/examples/code.py
manim_algorithm/examples/node.py
manim_algorithm/test/__init__.py
manim_algorithm/test/test_array.py
manim_algorithm/test/test_node.py
manim_algorithm/utils/__init__.py
manim_algorithm/utils/debug.py
manim_algorithm/utils/numpy_helper.py
manim_algorithm-0.0.4.dist-info/LICENSE
manim_algorithm-0.0.4.dist-info/METADATA
manim_algorithm-0.0.4.dist-info/WHEEL
manim_algorithm-0.0.4.dist-info/top_level.txt
manim_algorithm-0.0.4.dist-info/RECORD
