Metadata-Version: 2.1
Name: manim-algorithm
Version: 0.0.4
Summary: computer science lib for manim(ce version)
Home-page: https://github.com/sinianluoye/manim-algorithm
Author: sinianluoye
Author-email: sinianluoye@outlook.com
Classifier: Programming Language :: Python :: 3
Classifier: License :: OSI Approved :: MIT License
Classifier: Operating System :: OS Independent
Requires-Python: >=3.11
License-File: LICENSE
Requires-Dist: manim>=0.18.0
